README
setup.py
eggutils/__init__.py
eggutils/eggutils.py
eggutils.egg-info/PKG-INFO
eggutils.egg-info/SOURCES.txt
eggutils.egg-info/dependency_links.txt
eggutils.egg-info/entry_points.txt
eggutils.egg-info/top_level.txt