Metadata-Version: 1.0
Name: eggutils
Version: 0.0.2
Summary: A set of utilities to create/manipulate eggs
Home-page: http://pypi.python.org/pypi/eggutils
Author: David Cournapeau
Author-email: cournape@gmail.com
License: BSD
Platform: any
